fb_streamlit_auth/__init__.py
fb_streamlit_auth/frontend/dist/index.html
fb_streamlit_auth/frontend/dist/assets/index-DFSY0vrp.css
fb_streamlit_auth/frontend/dist/assets/index-P9iB9Rc1.js
fb_streamlit_auth-0.0.2.dist-info/LICENCE
fb_streamlit_auth-0.0.2.dist-info/LICENSE
fb_streamlit_auth-0.0.2.dist-info/METADATA
fb_streamlit_auth-0.0.2.dist-info/WHEEL
fb_streamlit_auth-0.0.2.dist-info/top_level.txt
fb_streamlit_auth-0.0.2.dist-info/RECORD
