Metadata-Version: 2.1
Name: fb_streamlit_auth
Version: 0.0.2
Summary: Streamlit component that allows you to implement Firebase login
Home-page: 
Author: Riccardo Trocca
Author-email: rtrocca@gmail.com
Requires-Python: >=3.7
License-File: LICENCE
License-File: LICENSE
Requires-Dist: streamlit >=0.63
Provides-Extra: devel
Requires-Dist: wheel ; extra == 'devel'
